libsprinkle/__init__.py
libsprinkle/clfile.py
libsprinkle/clsync.py
libsprinkle/common.py
libsprinkle/config.py
libsprinkle/exceptions.py
libsprinkle/operation.py
libsprinkle/rclone.py
libsprinkle/smtp_email.py
libsprinkle/sprinkle_daemon.py
sprinkle_py-1.0.0.data/scripts/sprinkle.py
sprinkle_py-1.0.0.dist-info/LICENSE
sprinkle_py-1.0.0.dist-info/METADATA
sprinkle_py-1.0.0.dist-info/WHEEL
sprinkle_py-1.0.0.dist-info/top_level.txt
sprinkle_py-1.0.0.dist-info/zip-safe
sprinkle_py-1.0.0.dist-info/RECORD
