Metadata-Version: 2.1
Name: sprinkle-py
Version: 1.0.0
Summary: Sprinkle is a volume clustering utility based on [RClone](https://rclone.org).
Home-page: https://gitlab.com/mmontuori/sprinkle
Author: mmontuori
Author-email: michael.montuori@gmail.com
License: GPLv3
Keywords: sprinkle cloud backup restore
Platform: UNKNOWN
Classifier: Development Status :: 5 - Production/Stable
Classifier: Intended Audience :: Developers
Classifier: Natural Language :: English
Requires-Dist: progress (>=1.4)
Requires-Dist: filelock (>=3.0.10)
Requires-Dist: daemons (>=1.3.0)
